nbbinder.py
nbbinder-0.13a5.dist-info/LICENSE
nbbinder-0.13a5.dist-info/METADATA
nbbinder-0.13a5.dist-info/WHEEL
nbbinder-0.13a5.dist-info/top_level.txt
nbbinder-0.13a5.dist-info/RECORD
