Metadata-Version: 2.1
Name: nbbinder
Version: 0.13a5
Summary: Generates a navigable book-like structure         to a collection of jupyter notebooks
Home-page: https://github.com/rmsrosa/nbbinder
Author: Ricardo M. S. Rosa
Author-email: rmsrosa@gmail.com
License: UNKNOWN
Project-URL: Documentation, https://nbbinder.readthedocs.io/
Project-URL: Source Code, https://github.com/rmsrosa/nbbinder
Platform: UNKNOWN
Classifier: Programming Language :: Python :: 3.5
Classifier: Programming Language :: Python :: 3.6
Classifier: Programming Language :: Python :: 3.7
Classifier: Programming Language :: Python :: 3.8
Classifier: Development Status :: 7 - Inactive
Classifier: Framework :: Jupyter
Classifier: Operating System :: MacOS
Classifier: Operating System :: POSIX :: Linux
Classifier: License :: OSI Approved :: MIT License
Requires-Python: >=3.5
